typer_htcondor/1.log
typer_htcondor/2.log
typer_htcondor/__init__.py
typer_htcondor/cli.py
typer_htcondor/dag.py
typer_htcondor/dagman.py
typer_htcondor/eventlog.py
typer_htcondor/eventlog.short
typer_htcondor/job copy.py
typer_htcondor/job.py
typer_htcondor/sites.log
typer_htcondor-0.1.6.dist-info/METADATA
typer_htcondor-0.1.6.dist-info/WHEEL
typer_htcondor-0.1.6.dist-info/entry_points.txt
typer_htcondor-0.1.6.dist-info/RECORD
