Metadata-Version: 2.1
Name: typer-htcondor
Version: 0.1.6
Summary: 
Author: Max Hartke
Author-email: hartke@cs.wisc.edu
Requires-Python: >=3.6,<4.0
Classifier: Programming Language :: Python :: 3
Classifier: Programming Language :: Python :: 3.6
Classifier: Programming Language :: Python :: 3.7
Classifier: Programming Language :: Python :: 3.8
Classifier: Programming Language :: Python :: 3.9
Classifier: Programming Language :: Python :: 3.10
Classifier: Programming Language :: Python :: 3.11
Classifier: Programming Language :: Python :: 3.12
Requires-Dist: htcondor (>=23.3.0,<24.0.0) ; python_version == "3.8"
Requires-Dist: typer[all] (>=0.9.0,<0.10.0)
